vk_bot/__init__.py
vk_bot/logging.py
vk_bot/types.py
vk_bot/vk_bot.py
VkBotLib-0.4.2.dist-info/LICENSE
VkBotLib-0.4.2.dist-info/METADATA
VkBotLib-0.4.2.dist-info/WHEEL
VkBotLib-0.4.2.dist-info/top_level.txt
VkBotLib-0.4.2.dist-info/RECORD
