Metadata-Version: 2.1
Name: VkBotLib
Version: 0.4.2
Summary: Python Vk bot api
Home-page: https://github.com/platun0v/vk_bot
Author: Platun0v
Author-email: platun0v@protonmail.com
License: Apache License, Version 2.0
Keywords: vk bot api tools
Platform: UNKNOWN
Classifier: Operating System :: OS Independent
Classifier: Programming Language :: Python :: 3
Classifier: Programming Language :: Python :: 3.6
Classifier: Programming Language :: Python :: 3.7
Classifier: License :: OSI Approved :: Apache Software License
Requires-Dist: requests
Requires-Dist: vk-api
